numbers_properties_pkg/__init__.py
numbers_properties_pkg/aakashvp.py
dubcountdown-2.dist-info/LICENSE
dubcountdown-2.dist-info/METADATA
dubcountdown-2.dist-info/WHEEL
dubcountdown-2.dist-info/top_level.txt
dubcountdown-2.dist-info/RECORD
